debtcloset/__init__.py
debtcloset/pyright/__init__.py
debtcloset/pyright/toml.py
debtcloset/ruff/__init__.py
debtcloset/ruff/toml.py
debtcloset-0.4.2.dist-info/METADATA
debtcloset-0.4.2.dist-info/WHEEL
debtcloset-0.4.2.dist-info/licenses/LICENSE
debtcloset-0.4.2.dist-info/RECORD
