Metadata-Version: 2.4
Name: debtcloset
Version: 0.4.2
Summary: Creation and maintenance of `exclude` file lists for common code quality tools.
Project-URL: Source, https://github.com/zkurtz/debtcloset
Author-email: Zach Kurtz <zkurtz@gmail.com>
License-File: LICENSE
Requires-Python: >=3.10
Requires-Dist: dummio>=1.5.0
Requires-Dist: listwrap>=0.0.3
